valued/__init__.py
valued-0.2.2.dist-info/METADATA
valued-0.2.2.dist-info/WHEEL
valued-0.2.2.dist-info/RECORD
