Metadata-Version: 2.1
Name: valued
Version: 0.2.2
Summary: 
Author: Support
Author-email: hello@valued.app
Requires-Python: >=3.10,<4.0
Classifier: Programming Language :: Python :: 3
Classifier: Programming Language :: Python :: 3.10
Classifier: Programming Language :: Python :: 3.11
Requires-Dist: requests (>=2.28.2,<3.0.0)
